microdns/__init__.py
microdns/__main__.py
microdns/microdns.py
microdns-1.0.3.dist-info/LICENSE
microdns-1.0.3.dist-info/METADATA
microdns-1.0.3.dist-info/NOTICE
microdns-1.0.3.dist-info/WHEEL
microdns-1.0.3.dist-info/entry_points.txt
microdns-1.0.3.dist-info/top_level.txt
microdns-1.0.3.dist-info/RECORD
