Metadata-Version: 2.1
Name: microdns
Version: 1.0.3
Summary: Micro DNS
Home-page: https://bitbucket.org/autestsuite/microdns
Author: Jesse Zhang
Author-email: jesse.zhang8759@gmail.com
License: Apache License 2.0
Platform: UNKNOWN
Classifier: Environment :: Console
Classifier: Intended Audience :: Developers
Classifier: License :: OSI Approved :: Apache Software License
Classifier: Operating System :: OS Independent
Classifier: Programming Language :: Python :: 3
Classifier: Programming Language :: Python :: 3.5
Requires-Dist: trlib
Requires-Dist: dnslib
